quantics/__init__.py
quantics/main.py
quantics-0.2.0.dist-info/METADATA
quantics-0.2.0.dist-info/WHEEL
quantics-0.2.0.dist-info/top_level.txt
quantics-0.2.0.dist-info/RECORD
