Metadata-Version: 2.1
Name: quantics
Version: 0.2.0
Author: Daniel Igbokwe
Author-email: igbodani14@gmail.com
Requires-Python: >=3.6
Requires-Dist: umap-learn
Requires-Dist: numpy
Requires-Dist: pandas
Requires-Dist: scikit-learn
